InquirerLib/InquirerPy/base/__init__.py
InquirerLib/InquirerPy/base/complex.py
InquirerLib/InquirerPy/base/control.py
InquirerLib/InquirerPy/base/list.py
InquirerLib/InquirerPy/base/simple.py
InquirerLib/InquirerPy/containers/__init__.py
InquirerLib/InquirerPy/containers/instruction.py
InquirerLib/InquirerPy/containers/message.py
InquirerLib/InquirerPy/containers/spinner.py
InquirerLib/InquirerPy/containers/validation.py
InquirerLib/InquirerPy/enum.py
InquirerLib/InquirerPy/exceptions.py
InquirerLib/InquirerPy/inquirer.py
InquirerLib/InquirerPy/prompts/__init__.py
InquirerLib/InquirerPy/prompts/checkbox.py
InquirerLib/InquirerPy/prompts/confirm.py
InquirerLib/InquirerPy/prompts/expand.py
InquirerLib/InquirerPy/prompts/filepath.py
InquirerLib/InquirerPy/prompts/fuzzy.py
InquirerLib/InquirerPy/prompts/input.py
InquirerLib/InquirerPy/prompts/list.py
InquirerLib/InquirerPy/prompts/number.py
InquirerLib/InquirerPy/prompts/rawlist.py
InquirerLib/InquirerPy/prompts/secret.py
InquirerLib/InquirerPy/resolver.py
InquirerLib/InquirerPy/separator.py
InquirerLib/InquirerPy/utils.py
InquirerLib/InquirerPy/validator.py
InquirerLib/__init__.py
InquirerLib/py.typed
inquirerlib-0.0.2.dist-info/LICENSE
inquirerlib-0.0.2.dist-info/METADATA
inquirerlib-0.0.2.dist-info/WHEEL
inquirerlib-0.0.2.dist-info/RECORD
