Metadata-Version: 2.1
Name: InquirerLib
Version: 0.0.2
Summary: An updated fork of InquirerPy - Python port of Inquirer.js (A collection of common interactive command-line user interfaces)
Home-page: https://github.com/brodybits/InquirerLib
License: MIT
Keywords: cli,prompt-toolkit,commandline,inquirer,development
Author: Various
Requires-Python: >=3.7,<4.0
Classifier: Development Status :: 2 - Pre-Alpha
Classifier: Environment :: Console
Classifier: Intended Audience :: Developers
Classifier: License :: OSI Approved :: MIT License
Classifier: Operating System :: Microsoft
Classifier: Operating System :: Unix
Classifier: Programming Language :: Python :: 3
Classifier: Programming Language :: Python :: 3.7
Classifier: Programming Language :: Python :: 3.8
Classifier: Programming Language :: Python :: 3.9
Classifier: Programming Language :: Python :: 3.10
Classifier: Programming Language :: Python :: 3.11
Classifier: Programming Language :: Python :: 3.12
Classifier: Topic :: Software Development
Classifier: Topic :: Software Development :: Libraries
Classifier: Topic :: Software Development :: Libraries :: Application Frameworks
Classifier: Topic :: Software Development :: User Interfaces
Provides-Extra: docs
Requires-Dist: Sphinx (>=4.1.2,<5.0.0) ; extra == "docs"
Requires-Dist: furo (>=2021.8.17-beta.43,<2022.0.0) ; extra == "docs"
Requires-Dist: myst-parser (>=0.15.1,<0.16.0) ; extra == "docs"
Requires-Dist: pfzy (>=0.3.1,<0.4.0)
Requires-Dist: prompt-toolkit (>=3.0.1,<4.0.0)
Requires-Dist: sphinx-autobuild (>=2021.3.14,<2022.0.0) ; extra == "docs"
Requires-Dist: sphinx-copybutton (>=0.4.0,<0.5.0) ; extra == "docs"
Project-URL: Repository, https://github.com/brodybits/InquirerLib
